gem_assist/__init__.py
gem_assist/core.py
gem_assist-0.2.0.dist-info/METADATA
gem_assist-0.2.0.dist-info/WHEEL
gem_assist-0.2.0.dist-info/top_level.txt
gem_assist-0.2.0.dist-info/RECORD
