Metadata-Version: 2.4
Name: gem-assist
Version: 0.2.0
Summary: A helper library for AI processing using Google Gemini.
Author-email: Your Name <your@email.com>
